{"Timestamp":"2026-06-10T05:51:49.4727933+04:00","Level":"Information","MessageTemplate":"SBERP.HumanResources starting...","Properties":{"MachineName":"SREE-PC","EnvironmentUserName":"SREE-PC\\Sreemonta"}}
{"Timestamp":"2026-06-10T05:51:54.4445992+04:00","Level":"Warning","MessageTemplate":"The WebRootPath was not found: {WebRootPath}. Static files may be unavailable.","Properties":{"WebRootPath":"D:\\Personal Work\\Project\\SB.Web\\SBERP.Services\\SBERP.HumanResources\\wwwroot","EventId":{"Id":16,"Name":"WebRootPathNotFound"},"SourceContext":"Microsoft.AspNetCore.StaticFiles.StaticFileMiddleware","MachineName":"SREE-PC","EnvironmentUserName":"SREE-PC\\Sreemonta"}}
{"Timestamp":"2026-06-10T05:52:07.5307395+04:00","Level":"Debug","MessageTemplate":"AuthenticationScheme: {AuthenticationScheme} was not authenticated.","TraceId":"2fe6aaf860ffbf8a34a73729b6a29b78","SpanId":"b2ac19f26b311735","Properties":{"AuthenticationScheme":"Bearer","EventId":{"Id":9,"Name":"AuthenticationSchemeNotAuthenticated"},"SourceContext":"Microsoft.AspNetCore.Authentication.JwtBearer.JwtBearerHandler","RequestId":"80000006-0003-f900-b63f-84710c7967bb","RequestPath":"/logo.png","MachineName":"SREE-PC","EnvironmentUserName":"SREE-PC\\Sreemonta"}}
{"Timestamp":"2026-06-10T05:52:07.5863951+04:00","Level":"Information","MessageTemplate":"HTTP {RequestMethod} {RequestPath} responded {StatusCode} in {Elapsed:0.0000} ms","TraceId":"2fe6aaf860ffbf8a34a73729b6a29b78","SpanId":"b2ac19f26b311735","Properties":{"RequestMethod":"GET","RequestPath":"/logo.png","StatusCode":404,"Elapsed":4133.9335,"SourceContext":"Serilog.AspNetCore.RequestLoggingMiddleware","RequestId":"80000006-0003-f900-b63f-84710c7967bb","MachineName":"SREE-PC","EnvironmentUserName":"SREE-PC\\Sreemonta"},"Renderings":{"Elapsed":[{"Format":"0.0000","Rendering":"4133.9335"}]}}
